Workbook
Name cambio: 'Premissas'!$B$5
Name fator_pico: 'Premissas'!$B$8
Name preco_mensal: 'Premissas'!$B$15
Name preco_semanal: 'Premissas'!$B$16
Name teto_mensal: 'Premissas'!$B$17
Name teto_semanal: 'Premissas'!$B$18
Name margem_alvo: 'Premissas'!$B$19
Name taxa_pct: 'Premissas'!$B$20
Name taxa_fixa: 'Premissas'!$B$21
Name infra_mes: 'Premissas'!$B$22
Name assinantes: 'Premissas'!$B$23
Name vida_meses: 'Premissas'!$B$24
Name sem_mes: 'Premissas'!$B$25
Name regen_pro: 'Premissas'!$B$40
Name regen_alav: 'Premissas'!$B$41
Name regen_flash: 'Premissas'!$B$42
Name custo_ger_hoje: 'Custo por geração'!$G$10
Name custo_ger_alav: 'Custo por geração'!$I$10
Name custo_ger_flash: 'Custo por geração'!$K$10
Name onboarding: 'Custo por geração'!$G$19
Name margem_tipico_mensal: 'Cenários de uso'!$G$6
Name margem_teto_mensal_pct: 'Cenários de uso'!$H$7
Name margem_tipico_pct: 'Cenários de uso'!$H$6
Name margem_teto_semanal_pct: 'Cenários de uso'!$H$15
Name margem_tipico_semanal: 'Cenários de uso'!$G$14
Name teto_na_margem_mensal: 'Teto mensal'!$B$13
Name teto_na_margem_semanal: 'Teto mensal'!$D$13
Name regen_virada: 'Regeneração x modelo'!$D$9
Name ltv_tipico_vida: 'LTV e CAC'!$B$26

Sheet Executiva
A1: Assistente Currículo: economics do plano pago
A2: Resumo para decisão. Tudo aqui é fórmula e vem das outras abas. Para mudar um número, edite a aba Premissas.
A4: Indicador | B4: Valor | C4: Unidade | D4: Como ler
A5: Custo por geração hoje (tudo em Pro) | B5: =custo_ger_hoje | C5: R$ por geração | D5: Estimativa. Substituir por medição do log de uso.
A6: Custo por geração com as alavancas | B6: =custo_ger_alav | C6: R$ por geração | D6: Flash em análise e conferência, Pro na geração.
A7: Redução de custo com as alavancas | B7: ='Custo por geração'!G12 | C7: % | D7: Só adotar depois que o eval mostrar que a qualidade se mantém.
A8: Custo de onboarding por assinante | B8: =onboarding | C8: R$ (uma vez) | D8: Entrevista, extração e leitura de CV.
A9: Preço do plano mensal | B9: =preco_mensal | C9: R$/mês | D9: Decisão: em torno de R$ 15.
A10: Teto mensal adotado | B10: =teto_mensal | C10: gerações/mês | D10: Aplicado em código (config.yaml).
A11: Teto mensal que sustenta a margem alvo | B11: =teto_na_margem_mensal | C11: gerações/mês | D11: Se for maior que o adotado, há folga para subir o teto.
A12: Margem no perfil típico (mensal) | B12: =margem_tipico_pct | C12: % da receita | D12: Perfil típico em Cenários de uso.
A13: Margem no teto (mensal) | B13: =margem_teto_mensal_pct | C13: % da receita | D13: Pior caso do plano mensal.
A14: Gerações por mês em que o mensal deixa de dar lucro | B14: ='Cenários de uso'!B17 | C14: gerações/mês | D14: Acima disso, cada geração custa mais do que sobra.
A15: Preço do plano semanal | B15: =preco_semanal | C15: R$/semana | D15: Hipótese a testar.
A16: Teto semanal adotado | B16: =teto_semanal | C16: gerações/semana | D16: Aplicado em código.
A17: Margem no teto (semanal) | B17: =margem_teto_semanal_pct | C17: % da receita | D17: Pior caso do plano semanal.
A18: Regeneração máxima do Flash em tudo para empatar com as alavancas | B18: =regen_virada | C18: extras por currículo | D18: Acima disso, o Flash em tudo sai mais caro por currículo entregue.
A19: LTV do assinante típico (vida média assumida) | B19: =ltv_tipico_vida | C19: R$ | D19: Margem recorrente do perfil típico x vida média da aba Premissas, menos onboarding.
A21: Leituras
A22: 1. O custo de IA domina a conta: a saída do modelo Pro na geração e na correção pesa mais que tudo. Reduzir correções e regerações vale tanto quanto trocar de modelo.
A23: 2. O teto de uso é a defesa da margem. Sem teto, um assinante em volume alto deixa o plano no prejuízo.
A24: 3. Os números de tokens são estimativas. A primeira ação é rodar com o log de uso ligado e trocar as premissas por medição.
A25: 4. A retenção é curta por natureza (quem emprega, cancela). O LTV é pequeno, por isso o CAC precisa ser quase zero (indicação, comunidades).
A26: 5. O semanal é prêmio por flexibilidade: o mesmo uso custa o mesmo, mas a receita por semana é maior que a fração do mensal.
A28: Legenda de cores
A29: Azul com fundo amarelo: entrada chave para editar
A30: Azul sem fundo: entrada secundária
A31: Preto: fórmula
A32: Verde: vínculo com outra aba

Sheet Premissas
A1: Premissas (única aba de entrada)
A2: Células azuis com fundo amarelo são entradas para editar. Todo o resto do arquivo é fórmula e recalcula. Estimativas de tokens vêm do tamanho dos prompts e dos logs locais; substituir por medição (log com campo 'uso') assim que houver.
A4: Câmbio e horário | B4: Valor | C4: Unidade | D4: Fonte ou nota
A5: Câmbio | B5: 5.5 | C5: R$ por US$ | D5: Placeholder: confirmar a cotação do dia.
A6: Multiplicador de preço no horário de pico | B6: 2 | C6: x | D6: DeepSeek: pico custa o dobro (api-docs.deepseek.com/quick_start/pricing, lido em 26/10/2026).
A7: Parcela do uso em horário de pico | B7: 0.15 | C7: % das chamadas | D7: Pico: 01h-04h e 06h-10h UTC, seg-sex (22h-01h e 03h-07h em Brasília). Estimativa: pouco uso nesses horários.
A8: Fator médio de preço (pico e fora do pico) | B8: =1+(B6-1)*B7 | C8: x | D8: Fórmula: multiplica o custo fora do pico.
A10: Modelo (preço por 1M de tokens, US$, fora do pico) | B10: Entrada cache hit | C10: Entrada cache miss | D10: Saída | E10: Fonte
A11: pro | B11: 0.022 | C11: 0.66 | D11: 1.98 | E11: deepseek-v4-pro | F11: api-docs.deepseek.com/quick_start/pricing, lido em 26/10/2026
A12: flash | B12: 0.003 | C12: 0.15 | D12: 0.6 | E12: deepseek-flash
A14: Planos e custos fixos | B14: Valor | C14: Unidade | D14: Fonte ou nota
A15: Preço do plano mensal | B15: 15 | C15: R$ | D15: Decisão do Felipe: em torno de R$ 15. A descoberta de preço pode mudar.
A16: Preço do plano semanal | B16: 7 | C16: R$ | D16: Hipótese (equivale a ~R$ 30 por mês). Testar com os interessados.
A17: Teto de gerações por mês | B17: 60 | C17: gerações | D17: config.yaml: planos.mensal.geracoes. Regeração conta como geração.
A18: Teto de gerações por semana | B18: 15 | C18: gerações | D18: config.yaml: planos.semanal.geracoes.
A19: Margem alvo para definir o teto | B19: 0.4 | C19: % da receita | D19: Escolha: 40% no teto de uso.
A20: Taxa de pagamento (% do valor) | B20: 0 | C20: % | D20: Pix direto na conta do Felipe, sem gateway.
A21: Taxa fixa por cobrança | B21: 0 | C21: R$ | D21: Idem.
A22: Custo fixo mensal de infraestrutura | B22: 40 | C22: R$/mês | D22: Placeholder: VPS e domínio. Confirmar.
A23: Assinantes ativos para ratear a infraestrutura | B23: 20 | C23: assinantes | D23: Hipótese do primeiro mês de operação.
A24: Vida média do assinante | B24: 3 | C24: meses | D24: Hipótese: quem consegue emprego cancela (2 a 4 meses).
A25: Semanas por mês | B25: 4.33 | C25: semanas | D25: Constante.
A27: Etapas de uma geração de currículo | B27: Chamadas por geração | C27: Tokens de entrada | D27: Tokens de saída | E27: % de entrada em cache | F27: Observação
A28: analisador | B28: 1 | C28: 5000 | D28: 1000 | E28: 0.3 | F28: Vaga + base confirmada. Saída: JSON da análise.
A29: verificador (termos duvidosos) | B29: 1 | C29: 3000 | D29: 500 | E29: 0.3 | F29: tailor.julgar_termos usa o rótulo 'verificador'.
A30: gerador | B30: 1 | C30: 9000 | D30: 4500 | E30: 0.35 | F30: Prompt de sistema (~12 KB) + vaga + análise + base. Saída ~13 a 16 mil caracteres (logs).
A31: gerador (correção) | B31: 0.3 | C31: 10000 | D31: 5000 | E31: 0.35 | F31: Até 2 correções por tamanho, nota ou plano; 0,3 é a frequência média assumida.
A32: verificador (final) | B32: 1 | C32: 4000 | D32: 1500 | E32: 0.3 | F32: Fiscal por IA sobre o texto gerado.
A34: Onboarding (uma vez por assinante, sempre em Pro) | B34: Chamadas | C34: Tokens de entrada | D34: Tokens de saída | E34: % de entrada em cache | F34: Observação
A35: entrevista (cerca de 12 turnos) | B35: 1 | C35: 60000 | D35: 1500 | E35: 0.5 | F35: Contexto cresce a cada turno: soma das entradas. Saídas curtas.
A36: extração da conversa | B36: 1 | C36: 6000 | D36: 3000 | E36: 0.3 | F36: interview.extrair_da_conversa.
A37: leitura de currículo importado | B37: 1 | C37: 4000 | D37: 3000 | E37: 0.3 | F37: Opcional; entra na conta como estimativa conservadora.
A39: Taxa de regeneração (gerações extras por currículo entregue) | B39: Valor | C39: Unidade | D39: Nota
A40: Tudo em Pro (hoje) | B40: 0.2 | C40: extras por currículo | D40: Hipótese: medir nos evals (n_correcoes e regerações dos usuários).
A41: Com alavancas (Flash em análise e conferência) | B41: 0.3 | C41: extras por currículo | D41: Hipótese: Flash nas etapas simples pode piorar um pouco a primeira geração.
A42: Flash em tudo | B42: 0.8 | C42: extras por currículo | D42: Hipótese: modelo mais fraco gera mais correções e mais regerações.

Sheet Custo por geração
A1: Custo por geração de currículo e de onboarding
A2: Fórmula por etapa: chamadas x (entrada x (hit x preço hit + (1 - hit) x preço miss) + saída x preço saída) / 1.000.000 x fator de pico x câmbio. Coluna de modelo é entrada (pro ou flash).
A4: Etapa | B4: Chamadas | C4: Tokens de entrada | D4: Tokens de saída | E4: % cache | F4: Modelo hoje | G4: Custo hoje (R$) | H4: Modelo com alavancas | I4: Custo com alavancas (R$) | J4: Modelo Flash em tudo | K4: Custo Flash em tudo (R$)
A5: =Premissas!A28 | B5: =Premissas!B28 | C5: =Premissas!C28 | D5: =Premissas!D28 | E5: =Premissas!E28 | F5: pro | G5: =B5*(C5*(E5*INDEX(Premissas!$B$11:$B$12,MATCH(F5,Premissas!$A$11:$A$12,0))+(1-E5)*INDEX(Premissas!$C$11:$C$12,MATCH(F5,Premissas!$A$11:$A$12,0)))+D5*INDEX(Premissas!$D$11:$D$12,MATCH(F5,Premissas!$A$11:$A$12,0)))/1000000*fator_pico*cambio | H5: flash | I5: =B5*(C5*(E5*INDEX(Premissas!$B$11:$B$12,MATCH(H5,Premissas!$A$11:$A$12,0))+(1-E5)*INDEX(Premissas!$C$11:$C$12,MATCH(H5,Premissas!$A$11:$A$12,0)))+D5*INDEX(Premissas!$D$11:$D$12,MATCH(H5,Premissas!$A$11:$A$12,0)))/1000000*fator_pico*cambio | J5: flash | K5: =B5*(C5*(E5*INDEX(Premissas!$B$11:$B$12,MATCH(J5,Premissas!$A$11:$A$12,0))+(1-E5)*INDEX(Premissas!$C$11:$C$12,MATCH(J5,Premissas!$A$11:$A$12,0)))+D5*INDEX(Premissas!$D$11:$D$12,MATCH(J5,Premissas!$A$11:$A$12,0)))/1000000*fator_pico*cambio
A6: =Premissas!A29 | B6: =Premissas!B29 | C6: =Premissas!C29 | D6: =Premissas!D29 | E6: =Premissas!E29 | F6: pro | G6: =B6*(C6*(E6*INDEX(Premissas!$B$11:$B$12,MATCH(F6,Premissas!$A$11:$A$12,0))+(1-E6)*INDEX(Premissas!$C$11:$C$12,MATCH(F6,Premissas!$A$11:$A$12,0)))+D6*INDEX(Premissas!$D$11:$D$12,MATCH(F6,Premissas!$A$11:$A$12,0)))/1000000*fator_pico*cambio | H6: flash | I6: =B6*(C6*(E6*INDEX(Premissas!$B$11:$B$12,MATCH(H6,Premissas!$A$11:$A$12,0))+(1-E6)*INDEX(Premissas!$C$11:$C$12,MATCH(H6,Premissas!$A$11:$A$12,0)))+D6*INDEX(Premissas!$D$11:$D$12,MATCH(H6,Premissas!$A$11:$A$12,0)))/1000000*fator_pico*cambio | J6: flash | K6: =B6*(C6*(E6*INDEX(Premissas!$B$11:$B$12,MATCH(J6,Premissas!$A$11:$A$12,0))+(1-E6)*INDEX(Premissas!$C$11:$C$12,MATCH(J6,Premissas!$A$11:$A$12,0)))+D6*INDEX(Premissas!$D$11:$D$12,MATCH(J6,Premissas!$A$11:$A$12,0)))/1000000*fator_pico*cambio
A7: =Premissas!A30 | B7: =Premissas!B30 | C7: =Premissas!C30 | D7: =Premissas!D30 | E7: =Premissas!E30 | F7: pro | G7: =B7*(C7*(E7*INDEX(Premissas!$B$11:$B$12,MATCH(F7,Premissas!$A$11:$A$12,0))+(1-E7)*INDEX(Premissas!$C$11:$C$12,MATCH(F7,Premissas!$A$11:$A$12,0)))+D7*INDEX(Premissas!$D$11:$D$12,MATCH(F7,Premissas!$A$11:$A$12,0)))/1000000*fator_pico*cambio | H7: pro | I7: =B7*(C7*(E7*INDEX(Premissas!$B$11:$B$12,MATCH(H7,Premissas!$A$11:$A$12,0))+(1-E7)*INDEX(Premissas!$C$11:$C$12,MATCH(H7,Premissas!$A$11:$A$12,0)))+D7*INDEX(Premissas!$D$11:$D$12,MATCH(H7,Premissas!$A$11:$A$12,0)))/1000000*fator_pico*cambio | J7: flash | K7: =B7*(C7*(E7*INDEX(Premissas!$B$11:$B$12,MATCH(J7,Premissas!$A$11:$A$12,0))+(1-E7)*INDEX(Premissas!$C$11:$C$12,MATCH(J7,Premissas!$A$11:$A$12,0)))+D7*INDEX(Premissas!$D$11:$D$12,MATCH(J7,Premissas!$A$11:$A$12,0)))/1000000*fator_pico*cambio
A8: =Premissas!A31 | B8: =Premissas!B31 | C8: =Premissas!C31 | D8: =Premissas!D31 | E8: =Premissas!E31 | F8: pro | G8: =B8*(C8*(E8*INDEX(Premissas!$B$11:$B$12,MATCH(F8,Premissas!$A$11:$A$12,0))+(1-E8)*INDEX(Premissas!$C$11:$C$12,MATCH(F8,Premissas!$A$11:$A$12,0)))+D8*INDEX(Premissas!$D$11:$D$12,MATCH(F8,Premissas!$A$11:$A$12,0)))/1000000*fator_pico*cambio | H8: pro | I8: =B8*(C8*(E8*INDEX(Premissas!$B$11:$B$12,MATCH(H8,Premissas!$A$11:$A$12,0))+(1-E8)*INDEX(Premissas!$C$11:$C$12,MATCH(H8,Premissas!$A$11:$A$12,0)))+D8*INDEX(Premissas!$D$11:$D$12,MATCH(H8,Premissas!$A$11:$A$12,0)))/1000000*fator_pico*cambio | J8: flash | K8: =B8*(C8*(E8*INDEX(Premissas!$B$11:$B$12,MATCH(J8,Premissas!$A$11:$A$12,0))+(1-E8)*INDEX(Premissas!$C$11:$C$12,MATCH(J8,Premissas!$A$11:$A$12,0)))+D8*INDEX(Premissas!$D$11:$D$12,MATCH(J8,Premissas!$A$11:$A$12,0)))/1000000*fator_pico*cambio
A9: =Premissas!A32 | B9: =Premissas!B32 | C9: =Premissas!C32 | D9: =Premissas!D32 | E9: =Premissas!E32 | F9: pro | G9: =B9*(C9*(E9*INDEX(Premissas!$B$11:$B$12,MATCH(F9,Premissas!$A$11:$A$12,0))+(1-E9)*INDEX(Premissas!$C$11:$C$12,MATCH(F9,Premissas!$A$11:$A$12,0)))+D9*INDEX(Premissas!$D$11:$D$12,MATCH(F9,Premissas!$A$11:$A$12,0)))/1000000*fator_pico*cambio | H9: flash | I9: =B9*(C9*(E9*INDEX(Premissas!$B$11:$B$12,MATCH(H9,Premissas!$A$11:$A$12,0))+(1-E9)*INDEX(Premissas!$C$11:$C$12,MATCH(H9,Premissas!$A$11:$A$12,0)))+D9*INDEX(Premissas!$D$11:$D$12,MATCH(H9,Premissas!$A$11:$A$12,0)))/1000000*fator_pico*cambio | J9: flash | K9: =B9*(C9*(E9*INDEX(Premissas!$B$11:$B$12,MATCH(J9,Premissas!$A$11:$A$12,0))+(1-E9)*INDEX(Premissas!$C$11:$C$12,MATCH(J9,Premissas!$A$11:$A$12,0)))+D9*INDEX(Premissas!$D$11:$D$12,MATCH(J9,Premissas!$A$11:$A$12,0)))/1000000*fator_pico*cambio
A10: Custo por geração completa | G10: =SUM(G5:G9) | I10: =SUM(I5:I9) | K10: =SUM(K5:K9)
A12: Redução do custo com as alavancas | G12: =1-I10/G10
A13: Redução com Flash em tudo | G13: =1-K10/G10
A15: Onboarding (Pro) | B15: Chamadas | C15: Tokens de entrada | D15: Tokens de saída | E15: % cache | F15: Modelo | G15: Custo (R$)
A16: =Premissas!A35 | B16: =Premissas!B35 | C16: =Premissas!C35 | D16: =Premissas!D35 | E16: =Premissas!E35 | F16: pro | G16: =B16*(C16*(E16*INDEX(Premissas!$B$11:$B$12,MATCH(F16,Premissas!$A$11:$A$12,0))+(1-E16)*INDEX(Premissas!$C$11:$C$12,MATCH(F16,Premissas!$A$11:$A$12,0)))+D16*INDEX(Premissas!$D$11:$D$12,MATCH(F16,Premissas!$A$11:$A$12,0)))/1000000*fator_pico*cambio
A17: =Premissas!A36 | B17: =Premissas!B36 | C17: =Premissas!C36 | D17: =Premissas!D36 | E17: =Premissas!E36 | F17: pro | G17: =B17*(C17*(E17*INDEX(Premissas!$B$11:$B$12,MATCH(F17,Premissas!$A$11:$A$12,0))+(1-E17)*INDEX(Premissas!$C$11:$C$12,MATCH(F17,Premissas!$A$11:$A$12,0)))+D17*INDEX(Premissas!$D$11:$D$12,MATCH(F17,Premissas!$A$11:$A$12,0)))/1000000*fator_pico*cambio
A18: =Premissas!A37 | B18: =Premissas!B37 | C18: =Premissas!C37 | D18: =Premissas!D37 | E18: =Premissas!E37 | F18: pro | G18: =B18*(C18*(E18*INDEX(Premissas!$B$11:$B$12,MATCH(F18,Premissas!$A$11:$A$12,0))+(1-E18)*INDEX(Premissas!$C$11:$C$12,MATCH(F18,Premissas!$A$11:$A$12,0)))+D18*INDEX(Premissas!$D$11:$D$12,MATCH(F18,Premissas!$A$11:$A$12,0)))/1000000*fator_pico*cambio
A19: Onboarding por assinante (uma vez) | G19: =SUM(G16:G18)

Sheet Cenários de uso
A1: Cenários de uso por assinante (margem recorrente, sem onboarding)
A2: Margem = receita - custo de IA - taxa de pagamento - infraestrutura rateada. Onboarding aparece na coluna do primeiro mês. Gerações por mês são entradas (azuis).
A4: Perfil mensal (plano mensal) | B4: Gerações por mês | C4: Custo de IA hoje (R$) | D4: Custo de IA com alavancas (R$) | E4: Taxa de pagamento (R$) | F4: Infra rateada (R$) | G4: Margem com alavancas (R$) | H4: Margem com alavancas (%) | I4: Margem hoje (%) | J4: Margem no 1º mês com alavancas (R$)
A5: Leve | B5: 10 | C5: =B5*custo_ger_hoje | D5: =B5*custo_ger_alav | E5: =preco_mensal*taxa_pct+taxa_fixa | F5: =infra_mes/assinantes | G5: =preco_mensal-D5-E5-F5 | H5: =IF(preco_mensal=0,0,G5/preco_mensal) | I5: =IF(preco_mensal=0,0,(preco_mensal-C5-E5-F5)/preco_mensal) | J5: =G5-onboarding
A6: Típico | B6: 30 | C6: =B6*custo_ger_hoje | D6: =B6*custo_ger_alav | E6: =preco_mensal*taxa_pct+taxa_fixa | F6: =infra_mes/assinantes | G6: =preco_mensal-D6-E6-F6 | H6: =IF(preco_mensal=0,0,G6/preco_mensal) | I6: =IF(preco_mensal=0,0,(preco_mensal-C6-E6-F6)/preco_mensal) | J6: =G6-onboarding
A7: No teto | B7: =teto_mensal | C7: =B7*custo_ger_hoje | D7: =B7*custo_ger_alav | E7: =preco_mensal*taxa_pct+taxa_fixa | F7: =infra_mes/assinantes | G7: =preco_mensal-D7-E7-F7 | H7: =IF(preco_mensal=0,0,G7/preco_mensal) | I7: =IF(preco_mensal=0,0,(preco_mensal-C7-E7-F7)/preco_mensal) | J7: =G7-onboarding
A8: Pesado sem teto | B8: 150 | C8: =B8*custo_ger_hoje | D8: =B8*custo_ger_alav | E8: =preco_mensal*taxa_pct+taxa_fixa | F8: =infra_mes/assinantes | G8: =preco_mensal-D8-E8-F8 | H8: =IF(preco_mensal=0,0,G8/preco_mensal) | I8: =IF(preco_mensal=0,0,(preco_mensal-C8-E8-F8)/preco_mensal) | J8: =G8-onboarding
A9: Extremo sem teto | B9: 250 | C9: =B9*custo_ger_hoje | D9: =B9*custo_ger_alav | E9: =preco_mensal*taxa_pct+taxa_fixa | F9: =infra_mes/assinantes | G9: =preco_mensal-D9-E9-F9 | H9: =IF(preco_mensal=0,0,G9/preco_mensal) | I9: =IF(preco_mensal=0,0,(preco_mensal-C9-E9-F9)/preco_mensal) | J9: =G9-onboarding
A12: Perfil semanal (plano semanal) | B12: Gerações por semana | C12: Custo de IA hoje (R$) | D12: Custo de IA com alavancas (R$) | E12: Taxa de pagamento (R$) | F12: Infra rateada (R$) | G12: Margem com alavancas (R$) | H12: Margem com alavancas (%) | I12: Margem hoje (%) | J12: Margem na 1ª semana com alavancas (R$)
A13: Leve | B13: 4 | C13: =B13*custo_ger_hoje | D13: =B13*custo_ger_alav | E13: =preco_semanal*taxa_pct+taxa_fixa | F13: =infra_mes/assinantes/sem_mes | G13: =preco_semanal-D13-E13-F13 | H13: =IF(preco_semanal=0,0,G13/preco_semanal) | I13: =IF(preco_semanal=0,0,(preco_semanal-C13-E13-F13)/preco_semanal) | J13: =G13-onboarding
A14: Típico | B14: 8 | C14: =B14*custo_ger_hoje | D14: =B14*custo_ger_alav | E14: =preco_semanal*taxa_pct+taxa_fixa | F14: =infra_mes/assinantes/sem_mes | G14: =preco_semanal-D14-E14-F14 | H14: =IF(preco_semanal=0,0,G14/preco_semanal) | I14: =IF(preco_semanal=0,0,(preco_semanal-C14-E14-F14)/preco_semanal) | J14: =G14-onboarding
A15: No teto | B15: =teto_semanal | C15: =B15*custo_ger_hoje | D15: =B15*custo_ger_alav | E15: =preco_semanal*taxa_pct+taxa_fixa | F15: =infra_mes/assinantes/sem_mes | G15: =preco_semanal-D15-E15-F15 | H15: =IF(preco_semanal=0,0,G15/preco_semanal) | I15: =IF(preco_semanal=0,0,(preco_semanal-C15-E15-F15)/preco_semanal) | J15: =G15-onboarding
A17: Gerações por mês em que o plano mensal empata (margem zero, com alavancas) | B17: =ROUNDDOWN((preco_mensal-E5-F5)/custo_ger_alav,0)

Sheet Teto mensal
A1: Teto de uso que sustenta uma margem alvo
A2: teto = (preço x (1 - margem alvo) - taxa - infra rateada - onboarding amortizado) / custo por geração. Onboarding amortizado = onboarding / vida média. Para o semanal, o teto é por semana.
A4: Margem alvo | B4: Mensal: gerações/mês (alavancas) | C4: Mensal: gerações/mês (hoje) | D4: Semanal: gerações/semana (alavancas) | E4: Semanal: gerações/semana (hoje)
A5: 0 | B5: =MAX(0,ROUNDDOWN((preco_mensal*(1-$A5)-(taxa_fixa+preco_mensal*taxa_pct)+infra_mes/assinantes+onboarding/vida_meses)/custo_ger_alav,0)) | C5: =MAX(0,ROUNDDOWN((preco_mensal*(1-$A5)-(taxa_fixa+preco_mensal*taxa_pct)+infra_mes/assinantes+onboarding/vida_meses)/custo_ger_hoje,0)) | D5: =MAX(0,ROUNDDOWN((preco_semanal*(1-$A5)-(taxa_fixa+preco_semanal*taxa_pct)+infra_mes/assinantes/sem_mes+onboarding/(vida_meses*sem_mes))/custo_ger_alav,0)) | E5: =MAX(0,ROUNDDOWN((preco_semanal*(1-$A5)-(taxa_fixa+preco_semanal*taxa_pct)+infra_mes/assinantes/sem_mes+onboarding/(vida_meses*sem_mes))/custo_ger_hoje,0))
A6: 0.2 | B6: =MAX(0,ROUNDDOWN((preco_mensal*(1-$A6)-(taxa_fixa+preco_mensal*taxa_pct)+infra_mes/assinantes+onboarding/vida_meses)/custo_ger_alav,0)) | C6: =MAX(0,ROUNDDOWN((preco_mensal*(1-$A6)-(taxa_fixa+preco_mensal*taxa_pct)+infra_mes/assinantes+onboarding/vida_meses)/custo_ger_hoje,0)) | D6: =MAX(0,ROUNDDOWN((preco_semanal*(1-$A6)-(taxa_fixa+preco_semanal*taxa_pct)+infra_mes/assinantes/sem_mes+onboarding/(vida_meses*sem_mes))/custo_ger_alav,0)) | E6: =MAX(0,ROUNDDOWN((preco_semanal*(1-$A6)-(taxa_fixa+preco_semanal*taxa_pct)+infra_mes/assinantes/sem_mes+onboarding/(vida_meses*sem_mes))/custo_ger_hoje,0))
A7: 0.3 | B7: =MAX(0,ROUNDDOWN((preco_mensal*(1-$A7)-(taxa_fixa+preco_mensal*taxa_pct)+infra_mes/assinantes+onboarding/vida_meses)/custo_ger_alav,0)) | C7: =MAX(0,ROUNDDOWN((preco_mensal*(1-$A7)-(taxa_fixa+preco_mensal*taxa_pct)+infra_mes/assinantes+onboarding/vida_meses)/custo_ger_hoje,0)) | D7: =MAX(0,ROUNDDOWN((preco_semanal*(1-$A7)-(taxa_fixa+preco_semanal*taxa_pct)+infra_mes/assinantes/sem_mes+onboarding/(vida_meses*sem_mes))/custo_ger_alav,0)) | E7: =MAX(0,ROUNDDOWN((preco_semanal*(1-$A7)-(taxa_fixa+preco_semanal*taxa_pct)+infra_mes/assinantes/sem_mes+onboarding/(vida_meses*sem_mes))/custo_ger_hoje,0))
A8: 0.4 | B8: =MAX(0,ROUNDDOWN((preco_mensal*(1-$A8)-(taxa_fixa+preco_mensal*taxa_pct)+infra_mes/assinantes+onboarding/vida_meses)/custo_ger_alav,0)) | C8: =MAX(0,ROUNDDOWN((preco_mensal*(1-$A8)-(taxa_fixa+preco_mensal*taxa_pct)+infra_mes/assinantes+onboarding/vida_meses)/custo_ger_hoje,0)) | D8: =MAX(0,ROUNDDOWN((preco_semanal*(1-$A8)-(taxa_fixa+preco_semanal*taxa_pct)+infra_mes/assinantes/sem_mes+onboarding/(vida_meses*sem_mes))/custo_ger_alav,0)) | E8: =MAX(0,ROUNDDOWN((preco_semanal*(1-$A8)-(taxa_fixa+preco_semanal*taxa_pct)+infra_mes/assinantes/sem_mes+onboarding/(vida_meses*sem_mes))/custo_ger_hoje,0))
A9: 0.5 | B9: =MAX(0,ROUNDDOWN((preco_mensal*(1-$A9)-(taxa_fixa+preco_mensal*taxa_pct)+infra_mes/assinantes+onboarding/vida_meses)/custo_ger_alav,0)) | C9: =MAX(0,ROUNDDOWN((preco_mensal*(1-$A9)-(taxa_fixa+preco_mensal*taxa_pct)+infra_mes/assinantes+onboarding/vida_meses)/custo_ger_hoje,0)) | D9: =MAX(0,ROUNDDOWN((preco_semanal*(1-$A9)-(taxa_fixa+preco_semanal*taxa_pct)+infra_mes/assinantes/sem_mes+onboarding/(vida_meses*sem_mes))/custo_ger_alav,0)) | E9: =MAX(0,ROUNDDOWN((preco_semanal*(1-$A9)-(taxa_fixa+preco_semanal*taxa_pct)+infra_mes/assinantes/sem_mes+onboarding/(vida_meses*sem_mes))/custo_ger_hoje,0))
A10: 0.6 | B10: =MAX(0,ROUNDDOWN((preco_mensal*(1-$A10)-(taxa_fixa+preco_mensal*taxa_pct)+infra_mes/assinantes+onboarding/vida_meses)/custo_ger_alav,0)) | C10: =MAX(0,ROUNDDOWN((preco_mensal*(1-$A10)-(taxa_fixa+preco_mensal*taxa_pct)+infra_mes/assinantes+onboarding/vida_meses)/custo_ger_hoje,0)) | D10: =MAX(0,ROUNDDOWN((preco_semanal*(1-$A10)-(taxa_fixa+preco_semanal*taxa_pct)+infra_mes/assinantes/sem_mes+onboarding/(vida_meses*sem_mes))/custo_ger_alav,0)) | E10: =MAX(0,ROUNDDOWN((preco_semanal*(1-$A10)-(taxa_fixa+preco_semanal*taxa_pct)+infra_mes/assinantes/sem_mes+onboarding/(vida_meses*sem_mes))/custo_ger_hoje,0))
A12: Teto adotado no config.yaml (mensal / semanal) | B12: =teto_mensal | D12: =teto_semanal
A13: Teto na margem alvo escolhida (alavancas) | B13: =MAX(0,ROUNDDOWN((preco_mensal*(1-margem_alvo)-(taxa_fixa+preco_mensal*taxa_pct)-infra_mes/assinantes-onboarding/vida_meses)/custo_ger_alav,0)) | D13: =MAX(0,ROUNDDOWN((preco_semanal*(1-margem_alvo)-(taxa_fixa+preco_semanal*taxa_pct)-infra_mes/assinantes/sem_mes-onboarding/(vida_meses*sem_mes))/custo_ger_alav,0))
A14: Folga do teto adotado em relação ao teto da margem alvo (positivo = há espaço para subir o teto) | B14: =B13-B12 | D14: =D13-D12

Sheet Regeneração x modelo
A1: Regeneração, modelo e custo por currículo entregue
A2: Custo por currículo entregue = custo por geração x (1 + taxa de regeneração). As taxas são hipóteses: o eval e o log de uso as medem. O ponto de virada mostra quanto o Flash em tudo poderia regenerar antes de custar mais que as alavancas.
A4: Configuração | B4: Custo por geração (R$) | C4: Taxa de regeneração (hipótese) | D4: Custo por currículo entregue (R$) | E4: Gerações do teto mensal que viram currículos entregues
A5: Tudo em Pro (hoje) | B5: =custo_ger_hoje | C5: =regen_pro | D5: =B5*(1+C5) | E5: =teto_mensal/(1+C5)
A6: Com alavancas (Flash em etapas simples) | B6: =custo_ger_alav | C6: =regen_alav | D6: =B6*(1+C6) | E6: =teto_mensal/(1+C6)
A7: Flash em tudo | B7: =custo_ger_flash | C7: =regen_flash | D7: =B7*(1+C7) | E7: =teto_mensal/(1+C7)
A9: Ponto de virada: regeneração máxima do Flash em tudo para empatar com as alavancas | D9: =D6/B7-1
A10: Folga em relação à taxa hipotética do Flash em tudo (positivo = Flash em tudo ainda sai mais barato) | D10: =D9-C7
A12: Sensibilidade: taxa de regeneração | B12: Tudo em Pro (R$ por entregue) | C12: Alavancas (R$ por entregue) | D12: Flash em tudo (R$ por entregue)
A13: 0 | B13: =custo_ger_hoje*(1+$A13) | C13: =custo_ger_alav*(1+$A13) | D13: =custo_ger_flash*(1+$A13)
A14: 0.25 | B14: =custo_ger_hoje*(1+$A14) | C14: =custo_ger_alav*(1+$A14) | D14: =custo_ger_flash*(1+$A14)
A15: 0.5 | B15: =custo_ger_hoje*(1+$A15) | C15: =custo_ger_alav*(1+$A15) | D15: =custo_ger_flash*(1+$A15)
A16: 1 | B16: =custo_ger_hoje*(1+$A16) | C16: =custo_ger_alav*(1+$A16) | D16: =custo_ger_flash*(1+$A16)
A17: 2 | B17: =custo_ger_hoje*(1+$A17) | C17: =custo_ger_alav*(1+$A17) | D17: =custo_ger_flash*(1+$A17)
A18: 3 | B18: =custo_ger_hoje*(1+$A18) | C18: =custo_ger_alav*(1+$A18) | D18: =custo_ger_flash*(1+$A18)
A20: Leitura: a regeneração multiplica o custo na mesma proporção em qualquer modelo. Por isso o limite de regerações por vaga (config.yaml: limites_uso.regeracoes_por_vaga) protege a margem tanto quanto a escolha do modelo.

Sheet LTV e CAC
A1: Valor do assinante e espaço para aquisição (CAC fica como observação)
A2: LTV = margem recorrente x meses ativos - onboarding. O CAC não entra no cálculo agora: preencha a célula amarela quando houver um canal, para ver o payback. Perfis vêm da aba Cenários de uso (típico e no teto), com alavancas.
A4: Meses ativos | B4: LTV perfil típico (R$) | C4: LTV no teto (R$) | D4: CAC máximo para empatar, típico (R$) | E4: CAC máximo para empatar, no teto (R$)
A5: 1 | B5: ='Cenários de uso'!$G$6*A5-onboarding | C5: ='Cenários de uso'!$G$7*A5-onboarding | D5: =MAX(0,B5) | E5: =MAX(0,C5)
A6: 2 | B6: ='Cenários de uso'!$G$6*A6-onboarding | C6: ='Cenários de uso'!$G$7*A6-onboarding | D6: =MAX(0,B6) | E6: =MAX(0,C6)
A7: 3 | B7: ='Cenários de uso'!$G$6*A7-onboarding | C7: ='Cenários de uso'!$G$7*A7-onboarding | D7: =MAX(0,B7) | E7: =MAX(0,C7)
A8: 4 | B8: ='Cenários de uso'!$G$6*A8-onboarding | C8: ='Cenários de uso'!$G$7*A8-onboarding | D8: =MAX(0,B8) | E8: =MAX(0,C8)
A9: 6 | B9: ='Cenários de uso'!$G$6*A9-onboarding | C9: ='Cenários de uso'!$G$7*A9-onboarding | D9: =MAX(0,B9) | E9: =MAX(0,C9)
A12: LTV do plano semanal (semanas ativas)
A13: Semanas ativas | B13: LTV perfil típico semanal (R$) | C13: LTV no teto semanal (R$)
A14: 1 | B14: ='Cenários de uso'!$G$14*A14-onboarding | C14: ='Cenários de uso'!$G$15*A14-onboarding
A15: 2 | B15: ='Cenários de uso'!$G$14*A15-onboarding | C15: ='Cenários de uso'!$G$15*A15-onboarding
A16: 4 | B16: ='Cenários de uso'!$G$14*A16-onboarding | C16: ='Cenários de uso'!$G$15*A16-onboarding
A17: 6 | B17: ='Cenários de uso'!$G$14*A17-onboarding | C17: ='Cenários de uso'!$G$15*A17-onboarding
A18: 8 | B18: ='Cenários de uso'!$G$14*A18-onboarding | C18: ='Cenários de uso'!$G$15*A18-onboarding
A21: Observação de CAC | B21: Valor
A22: CAC observado por assinante (R$), preencher quando houver canal
A23: Payback em meses no plano mensal (perfil típico) | B23: =IF(B22="","preencher o CAC",IF('Cenários de uso'!G6<=0,"margem não positiva",B22/'Cenários de uso'!G6))
A24: Meses ativos necessários para pagar o CAC e o onboarding (perfil típico) | B24: =IF(B22="","preencher o CAC",IF('Cenários de uso'!G6<=0,"margem não positiva",(B22+onboarding)/'Cenários de uso'!G6))
A25: Vida média assumida (meses), para comparar | B25: =vida_meses
A26: LTV do perfil típico com a vida média assumida (R$) | B26: ='Cenários de uso'!G6*vida_meses-onboarding
